bili_spyder/__init__.py
bili_spyder/rustwasm.py
bili_spyder/spyder.py
bili_spyder/stdweb.py
bili_spyder/data/e791556706f88d88b4846a61a583b31db007f83d.wasm
bili_spyder-0.2.0.dist-info/LICENSE
bili_spyder-0.2.0.dist-info/METADATA
bili_spyder-0.2.0.dist-info/WHEEL
bili_spyder-0.2.0.dist-info/top_level.txt
bili_spyder-0.2.0.dist-info/RECORD
