Metadata-Version: 2.1
Name: bili-spyder
Version: 0.2.0
Summary: Calculating the signature of the Bilibili's heartbeat requests
Home-page: https://github.com/acgnhiki/bili-spyder
Author: acgnhiki
Author-email: acgnhiki@outlook.com
License: UNKNOWN
Project-URL: Source Code, https://github.com/acgnhiki/bili-spyder/
Project-URL: Bug Tracker, https://github.com/acgnhiki/bili-spyder/issues
Keywords: bilibili,live,heartbeat,sign,spyder
Platform: UNKNOWN
Classifier: Development Status :: 4 - Beta
Classifier: Intended Audience :: Developers
Classifier: License :: OSI Approved :: GNU General Public License v3 (GPLv3)
Classifier: Operating System :: OS Independent
Classifier: Programming Language :: Python :: 3
Classifier: Programming Language :: Python :: 3.6
Classifier: Programming Language :: Python :: 3.7
Classifier: Programming Language :: Python :: 3.8
Classifier: Programming Language :: Python :: 3 :: Only
Requires-Python: >=3.6
Requires-Dist: wasmtime (>=0.19.0)
